graphs_kpineiro/__init__.py
graphs_kpineiro/heapq.py
graphs_kpineiro/sp.py
graphs_kpineiro-1.1.4.dist-info/METADATA
graphs_kpineiro-1.1.4.dist-info/WHEEL
graphs_kpineiro-1.1.4.dist-info/RECORD
