Metadata-Version: 2.3
Name: graphs_kpineiro
Version: 1.1.4
Summary: Homework 4 CS3250
Project-URL: Homepage, https://github.com/pypa/sampleproject
Project-URL: Bug Tracker, https://github.com/pypa/sampleproject/issues
Author-email: Kyle Pineiro <kpineiro@msudenver.edu>
Classifier: License :: OSI Approved :: MIT License
Classifier: Operating System :: OS Independent
Classifier: Programming Language :: Python :: 3
Requires-Python: >=3.7
